{
	"configurations" : 
	[
		{
			"directories" : 
			[
				{
					"build" : ".",
					"jsonFile" : "directory-.-Debug-f5ebdc15457944623624.json",
					"projectIndex" : 0,
					"source" : "."
				}
			],
			"name" : "Debug",
			"projects" : 
			[
				{
					"directoryIndexes" : 
					[
						0
					],
					"name" : "Project"
				}
			],
			"targets" : []
		}
	],
	"kind" : "codemodel",
	"paths" : 
	{
		"build" : "/Users/cedric/Library/Mobile Documents/com~apple~CloudDocs/School/Informatica 1/2 Project software engineering/PSE_Metro_Simulatie/cmake-build-debug",
		"source" : "/Users/cedric/Library/Mobile Documents/com~apple~CloudDocs/School/Informatica 1/2 Project software engineering/PSE_Metro_Simulatie"
	},
	"version" : 
	{
		"major" : 2,
		"minor" : 4
	}
}
